{
  "id": "maaskaratriadatalaamaljamia",
  "name": "معسكرات ريادة الأعمال الجامعية",
  "description": "يهدف المشروع إلى تطوير مشاريع ريادة الأعمال الجامعية عبر تطوير وتحويل الأفكار التجارية إلى مشاريع ريادية، وذلك عن طريق تقديم برامج لنشر ثقافة ريادة الأعمال.",
  "objectives": "رفع مستوى الوعي الريادي في المجتمع الجامعي، تفعيل دور الأندية الطلابية في نشر ثقافة ريادة الأعمال، توفير المعرفة اللازمة ومشاركة أفضل الممارسات.",
  "goals": [
    "تطوير مشاريع ريادة الأعمال الجامعية",
    "رفع مستوى الوعي الريادي داخل المجتمع الجامعي",
    "تعزيز مشاركة الطلاب والطالبات في الوسط الجامعي"
  ],
  "features": [
    "تقديم برامج متنوعة لنشر ثقافة ريادة الأعمال",
    "إقامة ورش عمل إعدادية",
    "جلسات إرشاد لمتابعة أداء المشاركين",
    "جلسات تحكيم لتقييم المشاريع"
  ],
  "eligibility_must": [
    "أن يكون المتقدم (طالب/ة، حديثو التخرج، الإداريون ومنسوبي الجامعات)",
    "أن يكون لديه فكرة مبدئية لحل المشكلة وأن يكون لها عائد مادي",
    "تعبئة نموذج التسجيل كاملًا وتوفير المعلومات الصحيحة",
    "الالتزام بجدول المبادرة"
  ],
  "sector_tags": [
    "ريادة أعمال",
    "تعليم",
    "جامعات"
  ],
  "stage_tags": [
    "فكرة",
    "MVP",
    "إطلاق"
  ],
  "url": "https://www.monshaat.gov.sa/ar/node/315408",
  "source_path": "/Volumes/Coding 1/Tuwaiq/OpportuMatch/data/002-معسكرات-ريادة-الأعمال-الجامعية.md",
  "last_updated": "2025-08-15T14:21:00",
  "launch_date": "2025",
  "funding_type": "in-kind",
  "funding_min": 0.0,
  "funding_max": 0.0,
  "program_type": "مبادرة/تمكين",
  "objectives_text": "يهدف البرنامج إلى تطوير مشاريع ريادة الأعمال الجامعية من خلال نشر ثقافة ريادة الأعمال."
}